setup.py
remotestatus/__init__.py
remotestatus/conf.py
remotestatus/models.py
remotestatus/remote.py
remotestatus/tasks.py
remotestatus/urls.py
remotestatus/views.py
remotestatus.egg-info/PKG-INFO
remotestatus.egg-info/SOURCES.txt
remotestatus.egg-info/dependency_links.txt
remotestatus.egg-info/requires.txt
remotestatus.egg-info/top_level.txt