Metadata-Version: 1.0
Name: remotestatus
Version: 0.1.1
Summary: A Django app that checks the status (and optional processes) of remote boxes and stores their values for viewing.
Home-page: https://github.com/cooncesean/remotestatus
Author: Sean Coonce
Author-email: cooncesean@gmail.com
License: LICENSE.txt
Platform: UNKNOWN
